cli_tool/.DS_Store
cli_tool/__init__.py
cli_tool/delete_model.py
cli_tool/download_setup.py
cli_tool/generate.py
cli_tool/json_utils.py
cli_tool/main.py
cli_tool/run_model.py
cli_tool/state.json
ezcmt-0.1.12.dist-info/METADATA
ezcmt-0.1.12.dist-info/WHEEL
ezcmt-0.1.12.dist-info/entry_points.txt
ezcmt-0.1.12.dist-info/top_level.txt
ezcmt-0.1.12.dist-info/RECORD
