Metadata-Version: 2.4
Name: ezcmt
Version: 0.1.12
Summary: A simple and free CLI tool for Git
Author: mmemoo
Requires-Python: >=3.10
Requires-Dist: gdown
Requires-Dist: ollama
Dynamic: requires-python
